{
  "chip": "CH32V30xxx",
  "group": "usbhd",
  "summary": {
    "peripheralCount": 1,
    "registerCount": 109,
    "fieldCount": 219
  },
  "peripherals": [
    {
      "name": "USBHD",
      "description": "USB register",
      "groupName": "USBHD",
      "baseAddress": "0x40023400",
      "interrupts": [
        {
          "name": "USBHSWakeup",
          "description": "USBHSWakeup",
          "value": 84
        },
        {
          "name": "USBHS",
          "description": "USBHS",
          "value": 85
        }
      ],
      "registers": [
        {
          "name": "USB_CTRL",
          "description": "USB base control",
          "addressOffset": "0x0000",
          "absoluteAddress": "0x40023400",
          "size": 8,
          "access": "read-write",
          "resetValue": "0x6",
          "fields": [
            {
              "name": "RB_UC_DMA_EN",
              "description": "DMA enable and DMA interrupt enable for USB"
            },
            {
              "name": "RB_UC_CLR_ALL",
              "description": "force clear FIFO and count of USB"
            },
            {
              "name": "RB_UC_RESET_SIE",
              "description": "force reset USB SIE, need software clear"
            },
            {
              "name": "RB_UC_INT_BUSY",
              "description": "enable automatic responding busy for device mode or automatic pause for host mode during interrupt flag UIF_TRANSFER valid"
            },
            {
              "name": "RB_UC_DEV_PU_EN",
              "description": "USB device enable and internal pullup resistance enable"
            },
            {
              "name": "RB_UC_SPEED_TYPE",
              "description": "enable USB low speed: 00=full speed, 01=high speed, 10 =low speed"
            },
            {
              "name": "RB_UC_HOST_MODE",
              "description": "enable USB host mode: 0=device mode, 1=host mode"
            }
          ]
        },
        {
          "name": "UHOST_CTRL",
          "description": "USB HOST control",
          "addressOffset": "0x0001",
          "absoluteAddress": "0x40023401",
          "size": 8,
          "fields": [
            {
              "name": "bUH_TX_BUS_RESET",
              "description": "USB host bus reset status",
              "access": "read-write"
            },
            {
              "name": "bUH_TX_BUS_SUSPEND",
              "description": "the host sends hang sigal",
              "access": "read-write"
            },
            {
              "name": "bUH_TX_BUS_RESUME",
              "description": "host wake up device",
              "access": "read-write"
            },
            {
              "name": "bUH_REMOTE_WKUP",
              "description": "the remoke wake-up",
              "access": "read-write"
            },
            {
              "name": "bUH_PHY_SUSPENDM",
              "description": "USB-PHY thesuspended state the internal USB-PLL is turned off",
              "access": "read-write"
            },
            {
              "name": "bUH_SOF_FREE",
              "description": "the bus is idle",
              "access": "read-only"
            },
            {
              "name": "bUH_SOF_EN",
              "description": "automatically generate the SOF packet enabling control bit",
              "access": "read-write"
            }
          ]
        },
        {
          "name": "USB_INT_EN",
          "description": "USB interrupt enable",
          "addressOffset": "0x0002",
          "absoluteAddress": "0x40023402",
          "size": 8,
          "access": "read-write",
          "resetValue": "0x0",
          "fields": [
            {
              "name": "RB_UIE_BUS_RST__RB_UIE_DETECT",
              "description": "enable interrupt for USB bus reset event for USB device mode;enable interrupt for USB device detected event for USB host mode"
            },
            {
              "name": "RB_UIE_TRANSFER",
              "description": "enable interrupt for USB transfer completion"
            },
            {
              "name": "RB_UIE_SUSPEND",
              "description": "enable interrupt for USB suspend or resume event"
            },
            {
              "name": "RB_UIE_SOF_ACT",
              "description": "indicate host SOF timer action status for USB host"
            },
            {
              "name": "RB_UIE_FIFO_OV",
              "description": "enable interrupt for FIFO overflow"
            },
            {
              "name": "RB_UIE_SETUP_ACT",
              "description": "indicate host SETUP timer action status for USB host"
            },
            {
              "name": "RB_UIE_ISO_ACT",
              "description": "enable interrupt for NAK responded for USB device mode"
            },
            {
              "name": "RB_UIE_DEV_NAK",
              "description": "enable interrupt for NAK responded for USB device mode"
            }
          ]
        },
        {
          "name": "USB_DEV_AD",
          "description": "USB device address",
          "addressOffset": "0x0003",
          "absoluteAddress": "0x40023403",
          "size": 8,
          "access": "read-write",
          "resetValue": "0x0",
          "fields": [
            {
              "name": "MASK_USB_ADDR",
              "description": "bit mask for USB device address"
            },
            {
              "name": "RB_UDA_GP_BIT",
              "description": "general purpose bit"
            }
          ]
        },
        {
          "name": "USB_FRAME_NO",
          "description": "USB_FRAME_NO",
          "addressOffset": "0x0004",
          "absoluteAddress": "0x40023404",
          "size": 16,
          "access": "read-only",
          "resetValue": "0x0",
          "fields": [
            {
              "name": "USB_FRAME_NO",
              "description": "USB_FRAME_NO"
            }
          ]
        },
        {
          "name": "USB_USB_SUSPEND",
          "description": "indicate USB suspend status",
          "addressOffset": "0x0006",
          "absoluteAddress": "0x40023406",
          "size": 8,
          "access": "read-write",
          "resetValue": "0x0",
          "fields": [
            {
              "name": "USB_SYS_MOD",
              "description": "USB_SYS_MOD"
            },
            {
              "name": "USB_WAKEUP",
              "description": "remote resume"
            },
            {
              "name": "USB_LINESTATE",
              "description": "USB_LINESTATE"
            }
          ]
        },
        {
          "name": "USB_SPEED_TYPE",
          "description": "USB_SPEED_TYPE",
          "addressOffset": "0x0008",
          "absoluteAddress": "0x40023408",
          "size": 8,
          "access": "read-only",
          "resetValue": "0x0",
          "fields": [
            {
              "name": "USB_SPEED_TYPE",
              "description": "USB_SPEED_TYPE"
            }
          ]
        },
        {
          "name": "USB_MIS_ST",
          "description": "USB miscellaneous status",
          "addressOffset": "0x0009",
          "absoluteAddress": "0x40023409",
          "size": 8,
          "access": "read-only",
          "resetValue": "0x0",
          "fields": [
            {
              "name": "RB_UMS_SPLIT_CAN",
              "description": "RO, indicate device attached status on USB host"
            },
            {
              "name": "RB_UMS_ATTACH",
              "description": "RO, indicate UDM level saved at device attached to USB host"
            },
            {
              "name": "RB_UMS_SUSPEND",
              "description": "RO, indicate USB suspend status"
            },
            {
              "name": "RB_UMS_BUS_RESET",
              "description": "RO, indicate USB bus reset status"
            },
            {
              "name": "RB_UMS_R_FIFO_RDY",
              "description": "RO, indicate USB receiving FIFO ready status (not empty)"
            },
            {
              "name": "RB_UMS_SIE_FREE",
              "description": "RO, indicate USB SIE free status"
            },
            {
              "name": "RB_UMS_SOF_ACT",
              "description": "RO, indicate host SOF timer action status for USB host"
            },
            {
              "name": "RB_UMS_SOF_PRES",
              "description": "RO, indicate host SOF timer presage status"
            }
          ]
        },
        {
          "name": "USB_INT_FG",
          "description": "USB interrupt flag",
          "addressOffset": "0x000A",
          "absoluteAddress": "0x4002340A",
          "size": 8,
          "resetValue": "0x20",
          "fields": [
            {
              "name": "RB_UIF_BUS_RST",
              "description": "RB_UIF_BUS_RST",
              "access": "read-write"
            },
            {
              "name": "RB_UIF_TRANSFER",
              "description": "USB transfer completion interrupt flag, direct bit address clear or write 1 to clear",
              "access": "read-write"
            },
            {
              "name": "RB_UIF_SUSPEND",
              "description": "USB suspend or resume event interrupt flag, direct bit address clear or write 1 to clear",
              "access": "read-write"
            },
            {
              "name": "RB_UIF_HST_SOF",
              "description": "host SOF timer interrupt flag for USB host, direct bit address clear or write 1 to clear",
              "access": "read-write"
            },
            {
              "name": "RB_UIF_FIFO_OV",
              "description": "FIFO overflow interrupt flag for USB, direct bit address clear or write 1 to clear",
              "access": "read-write"
            },
            {
              "name": "RB_U_SETUP_ACT",
              "description": "USB_SETUP_ACT",
              "access": "read-only"
            },
            {
              "name": "UIF_ISO_ACT",
              "description": "UIF_ISO_ACT",
              "access": "read-only"
            },
            {
              "name": "RB_U_IS_NAK",
              "description": "RO, indicate current USB transfer is NAK received",
              "access": "read-only"
            }
          ]
        },
        {
          "name": "USB_INT_ST",
          "description": "USB interrupt status",
          "addressOffset": "0x000B",
          "absoluteAddress": "0x4002340B",
          "size": 8,
          "access": "read-only",
          "fields": [
            {
              "name": "MASK_UIS_H_RES__MASK_UIS_ENDP",
              "description": "RO, bit mask of current transfer handshake response for USB host mode: 0000=no response, time out from device, others=handshake response PID received;RO, bit mask of current transfer endpoint number for USB device mode"
            },
            {
              "name": "MASK_UIS_TOKEN",
              "description": "RO, bit mask of current token PID code received for USB device mode"
            },
            {
              "name": "RB_UIS_TOG_OK",
              "description": "RO, indicate current USB transfer toggle is OK"
            },
            {
              "name": "RB_UIS_IS_NAK",
              "description": "RO, indicate current USB transfer is NAK received for USB device mode"
            }
          ]
        },
        {
          "name": "USB_RX_LEN",
          "description": "USB receiving length",
          "addressOffset": "0x000C",
          "absoluteAddress": "0x4002340C",
          "size": 16,
          "access": "read-only",
          "fields": [
            {
              "name": "R16_USB_RX_LEN",
              "description": "length of received bytes"
            }
          ]
        },
        {
          "name": "UEP_CONFIG",
          "description": "USB endpoint configuration",
          "addressOffset": "0x0010",
          "absoluteAddress": "0x40023410",
          "size": 32,
          "access": "read-write",
          "fields": [
            {
              "name": "bUEP_R_EN__UH_EP_MOD",
              "description": "endpoint RX enable/bUH_TX_EN",
              "access": "read-write"
            },
            {
              "name": "bUEP_T_EN_bUH_TX_EN",
              "description": "endpoint TX enable/bUH_TX_EN",
              "access": "read-write"
            }
          ]
        },
        {
          "name": "UEP_TYPE",
          "description": "USB endpoint type",
          "addressOffset": "0x0014",
          "absoluteAddress": "0x40023414",
          "size": 32,
          "access": "read-write",
          "fields": [
            {
              "name": "bUEP_R_TYPE",
              "description": "endpoint RX type",
              "access": "read-write"
            },
            {
              "name": "bUEP_T_TYPE",
              "description": "endpoint TX type",
              "access": "read-write"
            }
          ]
        },
        {
          "name": "UEP_BUF_MOD",
          "description": "USB endpoint buffer mode",
          "addressOffset": "0x0018",
          "absoluteAddress": "0x40023418",
          "size": 32,
          "access": "read-write",
          "fields": [
            {
              "name": "bUEP_ISO_BUF_MOD",
              "description": "buffer mode of USB endpoint",
              "access": "read-write"
            },
            {
              "name": "bUEP_BUF_MOD",
              "description": "buffer mode of USB endpoint",
              "access": "read-write"
            }
          ]
        },
        {
          "name": "UEP0_DMA",
          "description": "B endpoint 0 DMA buffer address",
          "addressOffset": "0x001C",
          "absoluteAddress": "0x4002341C",
          "size": 16,
          "access": "read-write",
          "fields": [
            {
              "name": "UEP0_DMA",
              "description": "endpoint 0 DMA buffer address",
              "access": "read-write"
            }
          ]
        },
        {
          "name": "UEP1_RX_DMA",
          "description": "endpoint 1 DMA RX buffer address",
          "addressOffset": "0x0020",
          "absoluteAddress": "0x40023420",
          "size": 16,
          "access": "read-write",
          "fields": [
            {
              "name": "UEP1_RX_DMA",
              "description": "endpoint 1 DMA buffer address",
              "access": "read-write"
            }
          ]
        },
        {
          "name": "UEP2_RX_DMA__UH_RX_DMA",
          "description": "endpoint 2 DMA RX buffer address/UH_RX_DMA",
          "addressOffset": "0x0024",
          "absoluteAddress": "0x40023424",
          "size": 16,
          "access": "read-write",
          "fields": [
            {
              "name": "UEP2_RX_DMA__UH_RX_DMA",
              "description": "endpoint 2 DMA buffer address",
              "access": "read-write"
            }
          ]
        },
        {
          "name": "UEP3_RX_DMA",
          "description": "endpoint 3 DMA RX buffer address",
          "addressOffset": "0x0028",
          "absoluteAddress": "0x40023428",
          "size": 16,
          "access": "read-write",
          "fields": [
            {
              "name": "UEP3_RX_DMA",
              "description": "endpoint 3 DMA buffer address",
              "access": "read-write"
            }
          ]
        },
        {
          "name": "UEP4_RX_DMA",
          "description": "endpoint 4 DMA RX buffer address",
          "addressOffset": "0x002C",
          "absoluteAddress": "0x4002342C",
          "size": 16,
          "access": "read-write",
          "fields": [
            {
              "name": "UEP4_RX_DMA",
              "description": "endpoint 4 DMA buffer address",
              "access": "read-write"
            }
          ]
        },
        {
          "name": "UEP5_RX_DMA",
          "description": "endpoint 5 DMA RX buffer address",
          "addressOffset": "0x0030",
          "absoluteAddress": "0x40023430",
          "size": 16,
          "access": "read-write",
          "fields": [
            {
              "name": "UEP5_DMA",
              "description": "endpoint 5 DMA buffer address",
              "access": "read-write"
            }
          ]
        },
        {
          "name": "UEP6_RX_DMA",
          "description": "endpoint 6 DMA RX buffer address",
          "addressOffset": "0x0034",
          "absoluteAddress": "0x40023434",
          "size": 16,
          "access": "read-write",
          "fields": [
            {
              "name": "UEP6_RX_DMA",
              "description": "endpoint 6 DMA buffer address",
              "access": "read-write"
            }
          ]
        },
        {
          "name": "UEP7_RX_DMA",
          "description": "endpoint 7 DMA RX buffer address",
          "addressOffset": "0x0038",
          "absoluteAddress": "0x40023438",
          "size": 16,
          "access": "read-write",
          "fields": [
            {
              "name": "UEP7_RX_DMA",
              "description": "endpoint 7 DMA buffer address",
              "access": "read-write"
            }
          ]
        },
        {
          "name": "UEP8_RX_DMA",
          "description": "endpoint 8 DMA RX buffer address",
          "addressOffset": "0x003C",
          "absoluteAddress": "0x4002343C",
          "size": 16,
          "access": "read-write",
          "fields": [
            {
              "name": "UEP8_RX_DMA",
              "description": "endpoint 8 DMA buffer address",
              "access": "read-write"
            }
          ]
        },
        {
          "name": "UEP9_RX_DMA",
          "description": "endpoint 9 DMA RX buffer address",
          "addressOffset": "0x0040",
          "absoluteAddress": "0x40023440",
          "size": 16,
          "access": "read-write",
          "fields": [
            {
              "name": "UEP9_RX_DMA",
              "description": "endpoint 9 DMA buffer address",
              "access": "read-write"
            }
          ]
        },
        {
          "name": "UEP10_RX_DMA",
          "description": "endpoint 10 DMA RX buffer address",
          "addressOffset": "0x0044",
          "absoluteAddress": "0x40023444",
          "size": 16,
          "access": "read-write",
          "fields": [
            {
              "name": "UEP10_RX_DMA",
              "description": "endpoint 10 DMA buffer address",
              "access": "read-write"
            }
          ]
        },
        {
          "name": "UEP11_RX_DMA",
          "description": "endpoint 11 DMA RX buffer address",
          "addressOffset": "0x0048",
          "absoluteAddress": "0x40023448",
          "size": 16,
          "access": "read-write",
          "fields": [
            {
              "name": "UEP11_RX_DMA",
              "description": "endpoint 11 DMA buffer address",
              "access": "read-write"
            }
          ]
        },
        {
          "name": "UEP12_RX_DMA",
          "description": "endpoint 12 DMA RX buffer address",
          "addressOffset": "0x004C",
          "absoluteAddress": "0x4002344C",
          "size": 16,
          "access": "read-write",
          "fields": [
            {
              "name": "UEP12_RX_DMA",
              "description": "endpoint 12 DMA buffer address",
              "access": "read-write"
            }
          ]
        },
        {
          "name": "UEP13_RX_DMA",
          "description": "endpoint 13 DMA RX buffer address",
          "addressOffset": "0x0050",
          "absoluteAddress": "0x40023450",
          "size": 16,
          "access": "read-write",
          "fields": [
            {
              "name": "UEP13_RX_DMA",
              "description": "endpoint 13 DMA buffer address",
              "access": "read-write"
            }
          ]
        },
        {
          "name": "UEP14_RX_DMA",
          "description": "endpoint 14 DMA RX buffer address",
          "addressOffset": "0x0054",
          "absoluteAddress": "0x40023454",
          "size": 16,
          "access": "read-write",
          "fields": [
            {
              "name": "UEP14_RX_DMA",
              "description": "endpoint 14 DMA buffer address",
              "access": "read-write"
            }
          ]
        },
        {
          "name": "UEP15_RX_DMA",
          "description": "endpoint 15 DMA RX buffer address",
          "addressOffset": "0x0058",
          "absoluteAddress": "0x40023458",
          "size": 16,
          "access": "read-write",
          "fields": [
            {
              "name": "UEP15_RX_DMA",
              "description": "endpoint 15 DMA buffer address",
              "access": "read-write"
            }
          ]
        },
        {
          "name": "UEP1_TX_DMA",
          "description": "endpoint 1 DMA TX buffer address",
          "addressOffset": "0x005C",
          "absoluteAddress": "0x4002345C",
          "size": 16,
          "access": "read-write",
          "fields": [
            {
              "name": "UEP1_TX_DMA",
              "description": "endpoint 1 DMA buffer address",
              "access": "read-write"
            }
          ]
        },
        {
          "name": "UEP2_TX_DMA",
          "description": "endpoint 2 DMA TX buffer address",
          "addressOffset": "0x0060",
          "absoluteAddress": "0x40023460",
          "size": 16,
          "access": "read-write",
          "fields": [
            {
              "name": "UEP2_TX_DMA",
              "description": "endpoint 2 DMA buffer address",
              "access": "read-write"
            }
          ]
        },
        {
          "name": "UEP3_TX_DMA__UH_TX_DMA",
          "description": "endpoint 3 DMA TX buffer address",
          "addressOffset": "0x0064",
          "absoluteAddress": "0x40023464",
          "size": 16,
          "access": "read-write",
          "fields": [
            {
              "name": "UEP3_TX_DMA__UH_TX_DMA",
              "description": "endpoint 3 DMA buffer address",
              "access": "read-write"
            }
          ]
        },
        {
          "name": "UEP4_TX_DMA",
          "description": "endpoint 4 DMA TX buffer address",
          "addressOffset": "0x0068",
          "absoluteAddress": "0x40023468",
          "size": 16,
          "access": "read-write",
          "fields": [
            {
              "name": "UEP4_TX_DMA",
              "description": "endpoint 4 DMA buffer address",
              "access": "read-write"
            }
          ]
        },
        {
          "name": "UEP5_TX_DMA",
          "description": "endpoint 5 DMA TX buffer address",
          "addressOffset": "0x006C",
          "absoluteAddress": "0x4002346C",
          "size": 16,
          "access": "read-write",
          "fields": [
            {
              "name": "UEP5_TX_DMA",
              "description": "endpoint 5 DMA buffer address",
              "access": "read-write"
            }
          ]
        },
        {
          "name": "UEP6_TX_DMA",
          "description": "endpoint 6 DMA TX buffer address",
          "addressOffset": "0x0070",
          "absoluteAddress": "0x40023470",
          "size": 16,
          "access": "read-write",
          "fields": [
            {
              "name": "UEP6_TX_DMA",
              "description": "endpoint 6 DMA buffer address",
              "access": "read-write"
            }
          ]
        },
        {
          "name": "UEP7_TX_DMA",
          "description": "endpoint 7 DMA TX buffer address",
          "addressOffset": "0x0074",
          "absoluteAddress": "0x40023474",
          "size": 16,
          "access": "read-write",
          "fields": [
            {
              "name": "UEP7_TX_DMA",
              "description": "endpoint 7 DMA buffer address",
              "access": "read-write"
            }
          ]
        },
        {
          "name": "UEP8_TX_DMA",
          "description": "endpoint 8 DMA TX buffer address",
          "addressOffset": "0x0078",
          "absoluteAddress": "0x40023478",
          "size": 16,
          "access": "read-write",
          "fields": [
            {
              "name": "UEP8_TX_DMA",
              "description": "endpoint 8 DMA buffer address",
              "access": "read-write"
            }
          ]
        },
        {
          "name": "UEP9_TX_DMA",
          "description": "endpoint 9 DMA TX buffer address",
          "addressOffset": "0x007C",
          "absoluteAddress": "0x4002347C",
          "size": 16,
          "access": "read-write",
          "fields": [
            {
              "name": "UEP9_TX_DMA",
              "description": "endpoint 9 DMA buffer address",
              "access": "read-write"
            }
          ]
        },
        {
          "name": "UEP10_TX_DMA",
          "description": "endpoint 10 DMA TX buffer address",
          "addressOffset": "0x0080",
          "absoluteAddress": "0x40023480",
          "size": 16,
          "access": "read-write",
          "fields": [
            {
              "name": "UEP10_TX_DMA",
              "description": "endpoint 10 DMA buffer address",
              "access": "read-write"
            }
          ]
        },
        {
          "name": "UEP11_TX_DMA",
          "description": "endpoint 11 DMA TX buffer address",
          "addressOffset": "0x0084",
          "absoluteAddress": "0x40023484",
          "size": 16,
          "access": "read-write",
          "fields": [
            {
              "name": "UEP11_TX_DMA",
              "description": "endpoint 11 DMA buffer address",
              "access": "read-write"
            }
          ]
        },
        {
          "name": "UEP12_TX_DMA____UH_SPLIT_DATA",
          "description": "endpoint 12 DMA TX buffer address",
          "addressOffset": "0x0088",
          "absoluteAddress": "0x40023488",
          "size": 16,
          "access": "read-write",
          "fields": [
            {
              "name": "UEP12_TX_DMA___UH_SPLIT_DATA",
              "description": "endpoint 12 DMA buffer address",
              "access": "read-write"
            }
          ]
        },
        {
          "name": "UEP13_TX_DMA",
          "description": "endpoint 13 DMA TX buffer address",
          "addressOffset": "0x008C",
          "absoluteAddress": "0x4002348C",
          "size": 16,
          "access": "read-write",
          "fields": [
            {
              "name": "UEP13_TX_DMA",
              "description": "endpoint 13 DMA buffer address",
              "access": "read-write"
            }
          ]
        },
        {
          "name": "UEP14_TX_DMA",
          "description": "endpoint 14 DMA TX buffer address",
          "addressOffset": "0x0090",
          "absoluteAddress": "0x40023490",
          "size": 16,
          "access": "read-write",
          "fields": [
            {
              "name": "UEP14_TX_DMA",
              "description": "endpoint 14 DMA buffer address",
              "access": "read-write"
            }
          ]
        },
        {
          "name": "UEP15_TX_DMA",
          "description": "endpoint 15 DMA TX buffer address",
          "addressOffset": "0x0094",
          "absoluteAddress": "0x40023494",
          "size": 16,
          "access": "read-write",
          "fields": [
            {
              "name": "UEP15_TX_DMA",
              "description": "endpoint 15 DMA buffer address",
              "access": "read-write"
            }
          ]
        },
        {
          "name": "UEP0_MAX_LEN",
          "description": "endpoint 0 max acceptable length",
          "addressOffset": "0x0098",
          "absoluteAddress": "0x40023498",
          "size": 16,
          "access": "read-write",
          "fields": [
            {
              "name": "UEP0_MAX_LEN",
              "description": "endpoint 0 max acceptable length",
              "access": "read-write"
            }
          ]
        },
        {
          "name": "UEP1_MAX_LEN",
          "description": "endpoint 1 max acceptable length",
          "addressOffset": "0x009C",
          "absoluteAddress": "0x4002349C",
          "size": 16,
          "access": "read-write",
          "fields": [
            {
              "name": "UEP1_MAX_LEN",
              "description": "endpoint 1 max acceptable length",
              "access": "read-write"
            }
          ]
        },
        {
          "name": "UEP2_MAX_LEN__UH_RX_MAX_LEN",
          "description": "endpoint 2 max acceptable length",
          "addressOffset": "0x00A0",
          "absoluteAddress": "0x400234A0",
          "size": 16,
          "access": "read-write",
          "fields": [
            {
              "name": "UEP2_MAX_LEN__UH_RX_MAX_LEN",
              "description": "endpoint 2 max acceptable length",
              "access": "read-write"
            }
          ]
        },
        {
          "name": "UEP3_MAX_LEN",
          "description": "endpoint 3 MAX_LEN TX",
          "addressOffset": "0x00A4",
          "absoluteAddress": "0x400234A4",
          "size": 16,
          "access": "read-write",
          "fields": [
            {
              "name": "UEP3_MAX_LEN",
              "description": "endpoint 3 max acceptable length",
              "access": "read-write"
            }
          ]
        },
        {
          "name": "UEP4_MAX_LEN",
          "description": "endpoint 4 max acceptable length",
          "addressOffset": "0x00A8",
          "absoluteAddress": "0x400234A8",
          "size": 16,
          "access": "read-write",
          "fields": [
            {
              "name": "UEP4_MAX_LEN",
              "description": "endpoint 4 max acceptable length",
              "access": "read-write"
            }
          ]
        },
        {
          "name": "UEP5_MAX_LEN",
          "description": "endpoint 5 max acceptable length",
          "addressOffset": "0x00AC",
          "absoluteAddress": "0x400234AC",
          "size": 16,
          "access": "read-write",
          "fields": [
            {
              "name": "UEP5_MAX_LEN",
              "description": "endpoint 5 max acceptable length",
              "access": "read-write"
            }
          ]
        },
        {
          "name": "UEP6_MAX_LEN",
          "description": "endpoint 6 max acceptable length",
          "addressOffset": "0x00B0",
          "absoluteAddress": "0x400234B0",
          "size": 16,
          "access": "read-write",
          "fields": [
            {
              "name": "UEP6_MAX_LEN",
              "description": "endpoint 6 max acceptable length",
              "access": "read-write"
            }
          ]
        },
        {
          "name": "UEP7_MAX_LEN",
          "description": "endpoint 7 max acceptable length",
          "addressOffset": "0x00B4",
          "absoluteAddress": "0x400234B4",
          "size": 16,
          "access": "read-write",
          "fields": [
            {
              "name": "UEP7_MAX_LEN",
              "description": "endpoint 7 max acceptable length",
              "access": "read-write"
            }
          ]
        },
        {
          "name": "UEP8_MAX_LEN",
          "description": "endpoint 8 max acceptable length",
          "addressOffset": "0x00B8",
          "absoluteAddress": "0x400234B8",
          "size": 16,
          "access": "read-write",
          "fields": [
            {
              "name": "UEP8_MAX_LEN",
              "description": "endpoint 8 max acceptable length",
              "access": "read-write"
            }
          ]
        },
        {
          "name": "UEP9_MAX_LEN",
          "description": "endpoint 9 max acceptable length",
          "addressOffset": "0x00BC",
          "absoluteAddress": "0x400234BC",
          "size": 16,
          "access": "read-write",
          "fields": [
            {
              "name": "UEP9_MAX_LEN",
              "description": "endpoint 9 max acceptable length",
              "access": "read-write"
            }
          ]
        },
        {
          "name": "UEP10_MAX_LEN",
          "description": "endpoint 10 max acceptable length",
          "addressOffset": "0x00C0",
          "absoluteAddress": "0x400234C0",
          "size": 16,
          "access": "read-write",
          "fields": [
            {
              "name": "UEP10_MAX_LEN",
              "description": "endpoint 10 max acceptable length",
              "access": "read-write"
            }
          ]
        },
        {
          "name": "UEP11_MAX_LEN",
          "description": "endpoint 11 max acceptable length",
          "addressOffset": "0x00C4",
          "absoluteAddress": "0x400234C4",
          "size": 16,
          "access": "read-write",
          "fields": [
            {
              "name": "UEP11_MAX_LEN",
              "description": "endpoint 11 max acceptable length",
              "access": "read-write"
            }
          ]
        },
        {
          "name": "UEP12_MAX_LEN",
          "description": "endpoint 12 max acceptable length",
          "addressOffset": "0x00C8",
          "absoluteAddress": "0x400234C8",
          "size": 16,
          "access": "read-write",
          "fields": [
            {
              "name": "UEP12_MAX_LEN",
              "description": "endpoint 12 max acceptable length",
              "access": "read-write"
            }
          ]
        },
        {
          "name": "UEP13_MAX_LEN",
          "description": "endpoint 13 max acceptable length",
          "addressOffset": "0x00CC",
          "absoluteAddress": "0x400234CC",
          "size": 16,
          "access": "read-write",
          "fields": [
            {
              "name": "UEP13_MAX_LEN",
              "description": "endpoint 13 max acceptable length",
              "access": "read-write"
            }
          ]
        },
        {
          "name": "UEP14_MAX_LEN",
          "description": "endpoint 14 max acceptable length",
          "addressOffset": "0x00D0",
          "absoluteAddress": "0x400234D0",
          "size": 16,
          "access": "read-write",
          "fields": [
            {
              "name": "UEP14_MAX_LEN",
              "description": "endpoint 14 max acceptable length",
              "access": "read-write"
            }
          ]
        },
        {
          "name": "UEP15_MAX_LEN",
          "description": "endpoint 15 max acceptable length",
          "addressOffset": "0x00D4",
          "absoluteAddress": "0x400234D4",
          "size": 16,
          "access": "read-write",
          "fields": [
            {
              "name": "UEP15_MAX_LEN",
              "description": "endpoint 15 max acceptable length",
              "access": "read-write"
            }
          ]
        },
        {
          "name": "UEP0_T_LEN",
          "description": "endpoint 0 send the length",
          "addressOffset": "0x00D8",
          "absoluteAddress": "0x400234D8",
          "size": 16,
          "access": "read-write",
          "fields": [
            {
              "name": "UEP0_T_LEN",
              "description": "endpoint 0 send the length",
              "access": "read-write"
            }
          ]
        },
        {
          "name": "UEP0_T_CTRL",
          "description": "endpoint 0 send control",
          "addressOffset": "0x00DA",
          "absoluteAddress": "0x400234DA",
          "size": 8,
          "access": "read-write",
          "fields": [
            {
              "name": "MASK_UEP_T_RES",
              "description": "endpoint 0 control of the send response to IN transactions",
              "access": "read-write"
            },
            {
              "name": "MASK_UEP_T_TOG",
              "description": "endpoint 0 synchronous trigger bit for the sender to prepare",
              "access": "read-write"
            },
            {
              "name": "bUEP_T_TOG_AUTO",
              "description": "endpoint 0 synchronous trigger bit automatic filp enables the control bit",
              "access": "read-write"
            }
          ]
        },
        {
          "name": "UEP0_R_CTRL",
          "description": "endpoint 0 send control",
          "addressOffset": "0x00DB",
          "absoluteAddress": "0x400234DB",
          "size": 8,
          "access": "read-write",
          "fields": [
            {
              "name": "MASK_UEP_R_RES",
              "description": "endpoint 0 control of the accept response to OUT transactions",
              "access": "read-write"
            },
            {
              "name": "MASK_UEP_R_TOG",
              "description": "endpoint 0 synchronous trigger bit for the accept to prepare",
              "access": "read-write"
            },
            {
              "name": "bUEP_R_TOG_AUTO",
              "description": "endpoint 0 synchronous trigger bit automatic filp enables the control bit",
              "access": "read-only"
            }
          ]
        },
        {
          "name": "UEP1_T_LEN",
          "description": "endpoint 1 send the length",
          "addressOffset": "0x00DC",
          "absoluteAddress": "0x400234DC",
          "size": 16,
          "access": "read-write",
          "fields": [
            {
              "name": "UEP1_T_LEN",
              "description": "endpoint 1 send the length",
              "access": "read-write"
            }
          ]
        },
        {
          "name": "UEP1_T_CTRL",
          "description": "endpoint 1 send control",
          "addressOffset": "0x00DE",
          "absoluteAddress": "0x400234DE",
          "size": 8,
          "access": "read-write",
          "fields": [
            {
              "name": "MASK_UEP_T_RES",
              "description": "endpoint 1 control of the send response to IN transactions",
              "access": "read-write"
            },
            {
              "name": "MASK_UEP_T_TOG",
              "description": "endpoint 1 synchronous trigger bit for the sender to prepare",
              "access": "read-write"
            },
            {
              "name": "bUEP_T_TOG_AUTO",
              "description": "endpoint 1 synchronous trigger bit automatic filp enables the control bit",
              "access": "read-write"
            }
          ]
        },
        {
          "name": "UEP1_R_CTRL",
          "description": "endpoint 1 send control",
          "addressOffset": "0x00DF",
          "absoluteAddress": "0x400234DF",
          "size": 8,
          "access": "read-write",
          "fields": [
            {
              "name": "MASK_UEP_R_RES",
              "description": "endpoint 1 control of the accept response to OUT transactions",
              "access": "read-write"
            },
            {
              "name": "MASK_UEP_R_TOG",
              "description": "endpoint 1 synchronous trigger bit for the accept to prepare",
              "access": "read-write"
            },
            {
              "name": "bUEP_R_TOG_AUTO",
              "description": "endpoint 1 synchronous trigger bit automatic filp enables the control bit",
              "access": "read-only"
            }
          ]
        },
        {
          "name": "UEP2_T_LEN__UH_EP_PID",
          "description": "endpoint 2 send the length",
          "addressOffset": "0x00E0",
          "absoluteAddress": "0x400234E0",
          "size": 16,
          "access": "read-write",
          "fields": [
            {
              "name": "UEP2_T_LEN__MASK_UH_ENDP__MASK_UH_TOKEN",
              "description": "endpoint 2 send the length",
              "access": "read-write"
            }
          ]
        },
        {
          "name": "UEP2_T_CTRL",
          "description": "endpoint 2 send control",
          "addressOffset": "0x00E2",
          "absoluteAddress": "0x400234E2",
          "size": 8,
          "access": "read-write",
          "fields": [
            {
              "name": "MASK_UEP_T_RES",
              "description": "endpoint 2 control of the send response to IN transactions",
              "access": "read-write"
            },
            {
              "name": "MASK_UEP_T_TOG",
              "description": "endpoint 2 synchronous trigger bit for the sender to prepare",
              "access": "read-write"
            },
            {
              "name": "bUEP_T_TOG_AUTO",
              "description": "endpoint 2 synchronous trigger bit automatic filp enables the control bit",
              "access": "read-write"
            }
          ]
        },
        {
          "name": "UEP2_R_CTRL__UH_RX_CTRL",
          "description": "endpoint 2 send control",
          "addressOffset": "0x00E3",
          "absoluteAddress": "0x400234E3",
          "size": 8,
          "access": "read-write",
          "fields": [
            {
              "name": "MASK_UEP_R_RES__MASK_UH_R_RES",
              "description": "endpoint 2 control of the accept response to OUT transactions",
              "access": "read-write"
            },
            {
              "name": "bUH_R_RES_NO",
              "description": "bUH_R_RES_NO",
              "access": "read-write"
            },
            {
              "name": "MASK_UEP_R_TOG__MASK_UH_R_TOG",
              "description": "endpoint 2 synchronous trigger bit for the accept to prepare",
              "access": "read-write"
            },
            {
              "name": "bUEP_R_TOG_AUTO__bUH_R_AUTO_TOG",
              "description": "endpoint 2 synchronous trigger bit automatic filp enables the control bit",
              "access": "read-only"
            },
            {
              "name": "bUH_R_DATA_NO",
              "description": "bUH_R_DATA_NO",
              "access": "read-write"
            }
          ]
        },
        {
          "name": "UEP3_T_LEN___UH_TX_LEN_H",
          "description": "endpoint 3 send the length",
          "addressOffset": "0x00E4",
          "absoluteAddress": "0x400234E4",
          "size": 16,
          "access": "read-write",
          "fields": [
            {
              "name": "UEP3_T_LEN___UH_TX_LEN_H",
              "description": "endpoint 3 send the length",
              "access": "read-write"
            }
          ]
        },
        {
          "name": "UEP3_T_CTRL___UH_TX_CTRL",
          "description": "endpoint 3 send control",
          "addressOffset": "0x00E6",
          "absoluteAddress": "0x400234E6",
          "size": 8,
          "access": "read-write",
          "fields": [
            {
              "name": "MASK_UEP_T_RES_____MASK_UH_T_RES",
              "description": "endpoint 3 control of the send response to IN transactions",
              "access": "read-write"
            },
            {
              "name": "bUH_T_RES_NO",
              "description": "bUH_T_RES_NO",
              "access": "read-write"
            },
            {
              "name": "MASK_UEP_T_TOG____MASK_UH_T_TOG",
              "description": "endpoint 3 synchronous trigger bit for the sender to prepare",
              "access": "read-write"
            },
            {
              "name": "bUEP_T_TOG_AUTO____bUH_T_AUTO_TOG",
              "description": "endpoint 3 synchronous trigger bit automatic filp enables the control bit",
              "access": "read-write"
            },
            {
              "name": "bUH_T_DATA_NO",
              "description": "bUH_T_DATA_NO",
              "access": "read-write"
            }
          ]
        },
        {
          "name": "UEP3_R_CTRL",
          "description": "endpoint 3 send control",
          "addressOffset": "0x00E7",
          "absoluteAddress": "0x400234E7",
          "size": 8,
          "access": "read-write",
          "fields": [
            {
              "name": "MASK_UEP_R_RES",
              "description": "endpoint 3 control of the accept response to OUT transactions",
              "access": "read-write"
            },
            {
              "name": "MASK_UEP_R_TOG",
              "description": "endpoint 3 synchronous trigger bit for the accept to prepare",
              "access": "read-write"
            },
            {
              "name": "bUEP_R_TOG_AUTO",
              "description": "endpoint 3 synchronous trigger bit automatic filp enables the control bit",
              "access": "read-only"
            }
          ]
        },
        {
          "name": "UEP4_T_LEN",
          "description": "endpoint 4 send the length",
          "addressOffset": "0x00E8",
          "absoluteAddress": "0x400234E8",
          "size": 16,
          "access": "read-write",
          "fields": [
            {
              "name": "UEP4_T_LEN",
              "description": "endpoint 0 send the length",
              "access": "read-write"
            }
          ]
        },
        {
          "name": "UEP4_T_CTRL",
          "description": "endpoint 4 send control",
          "addressOffset": "0x00EA",
          "absoluteAddress": "0x400234EA",
          "size": 8,
          "access": "read-write",
          "fields": [
            {
              "name": "MASK_UEP_T_RES",
              "description": "endpoint 4 control of the send response to IN transactions",
              "access": "read-write"
            },
            {
              "name": "MASK_UEP_T_TOG",
              "description": "endpoint 4 synchronous trigger bit for the sender to prepare",
              "access": "read-write"
            },
            {
              "name": "bUEP_T_TOG_AUTO",
              "description": "endpoint 4 synchronous trigger bit automatic filp enables the control bit",
              "access": "read-write"
            }
          ]
        },
        {
          "name": "UEP4_R_CTRL",
          "description": "endpoint 4 send control",
          "addressOffset": "0x00EB",
          "absoluteAddress": "0x400234EB",
          "size": 8,
          "access": "read-write",
          "fields": [
            {
              "name": "MASK_UEP_R_RES",
              "description": "endpoint 4 control of the accept response to OUT transactions",
              "access": "read-write"
            },
            {
              "name": "MASK_UEP_R_TOG",
              "description": "endpoint 4 synchronous trigger bit for the accept to prepare",
              "access": "read-write"
            },
            {
              "name": "bUEP_R_TOG_AUTO",
              "description": "endpoint 4 synchronous trigger bit automatic filp enables the control bit",
              "access": "read-only"
            }
          ]
        },
        {
          "name": "UEP5_T_LEN",
          "description": "endpoint 5 send the length",
          "addressOffset": "0x00EC",
          "absoluteAddress": "0x400234EC",
          "size": 16,
          "access": "read-write",
          "fields": [
            {
              "name": "UEP5_T_LEN",
              "description": "endpoint 5 send the length",
              "access": "read-write"
            }
          ]
        },
        {
          "name": "UEP5_T_CTRL",
          "description": "endpoint 5 send control",
          "addressOffset": "0x00EE",
          "absoluteAddress": "0x400234EE",
          "size": 8,
          "access": "read-write",
          "fields": [
            {
              "name": "MASK_UEP_T_RES",
              "description": "endpoint 5 control of the send response to IN transactions",
              "access": "read-write"
            },
            {
              "name": "MASK_UEP_T_TOG",
              "description": "endpoint 5 synchronous trigger bit for the sender to prepare",
              "access": "read-write"
            },
            {
              "name": "bUEP_T_TOG_AUTO",
              "description": "endpoint 5 synchronous trigger bit automatic filp enables the control bit",
              "access": "read-write"
            }
          ]
        },
        {
          "name": "UEP5_R_CTRL",
          "description": "endpoint 5 send control",
          "addressOffset": "0x00EF",
          "absoluteAddress": "0x400234EF",
          "size": 8,
          "access": "read-write",
          "fields": [
            {
              "name": "MASK_UEP_R_RES",
              "description": "endpoint 5 control of the accept response to OUT transactions",
              "access": "read-write"
            },
            {
              "name": "MASK_UEP_R_TOG",
              "description": "endpoint 5 synchronous trigger bit for the accept to prepare",
              "access": "read-write"
            },
            {
              "name": "bUEP_R_TOG_AUTO",
              "description": "endpoint 5 synchronous trigger bit automatic filp enables the control bit",
              "access": "read-only"
            }
          ]
        },
        {
          "name": "UEP6_T_LEN",
          "description": "endpoint 6 send the length",
          "addressOffset": "0x00F0",
          "absoluteAddress": "0x400234F0",
          "size": 16,
          "access": "read-write",
          "fields": [
            {
              "name": "UEP6_T_LEN",
              "description": "endpoint 6 send the length",
              "access": "read-write"
            }
          ]
        },
        {
          "name": "UEP6_T_CTRL",
          "description": "endpoint 6 send control",
          "addressOffset": "0x00F2",
          "absoluteAddress": "0x400234F2",
          "size": 8,
          "access": "read-write",
          "fields": [
            {
              "name": "MASK_UEP_T_RES",
              "description": "endpoint 6 control of the send response to IN transactions",
              "access": "read-write"
            },
            {
              "name": "MASK_UEP_T_TOG",
              "description": "endpoint 6 synchronous trigger bit for the sender to prepare",
              "access": "read-write"
            },
            {
              "name": "bUEP_T_TOG_AUTO",
              "description": "endpoint 6 synchronous trigger bit automatic filp enables the control bit",
              "access": "read-write"
            }
          ]
        },
        {
          "name": "UEP6_R_CTRL",
          "description": "endpoint 6 send control",
          "addressOffset": "0x00F3",
          "absoluteAddress": "0x400234F3",
          "size": 8,
          "access": "read-write",
          "fields": [
            {
              "name": "MASK_UEP_R_RES",
              "description": "endpoint 6 control of the accept response to OUT transactions",
              "access": "read-write"
            },
            {
              "name": "MASK_UEP_R_TOG",
              "description": "endpoint 6 synchronous trigger bit for the accept to prepare",
              "access": "read-write"
            },
            {
              "name": "bUEP_R_TOG_AUTO",
              "description": "endpoint 6 synchronous trigger bit automatic filp enables the control bit",
              "access": "read-only"
            }
          ]
        },
        {
          "name": "UEP7_T_LEN",
          "description": "endpoint 7 send the length",
          "addressOffset": "0x00F4",
          "absoluteAddress": "0x400234F4",
          "size": 16,
          "access": "read-write",
          "fields": [
            {
              "name": "UEP7_T_LEN",
              "description": "endpoint 7 send the length",
              "access": "read-write"
            }
          ]
        },
        {
          "name": "UEP7_T_CTRL",
          "description": "endpoint 7 send control",
          "addressOffset": "0x00F6",
          "absoluteAddress": "0x400234F6",
          "size": 8,
          "access": "read-write",
          "fields": [
            {
              "name": "MASK_UEP_T_RES",
              "description": "endpoint 7 control of the send response to IN transactions",
              "access": "read-write"
            },
            {
              "name": "MASK_UEP_T_TOG",
              "description": "endpoint 7 synchronous trigger bit for the sender to prepare",
              "access": "read-write"
            },
            {
              "name": "bUEP_T_TOG_AUTO",
              "description": "endpoint 7 synchronous trigger bit automatic filp enables the control bit",
              "access": "read-write"
            }
          ]
        },
        {
          "name": "UEP7_R_CTRL",
          "description": "endpoint 7 send control",
          "addressOffset": "0x00F7",
          "absoluteAddress": "0x400234F7",
          "size": 8,
          "access": "read-write",
          "fields": [
            {
              "name": "MASK_UEP_R_RES",
              "description": "endpoint 7 control of the accept response to OUT transactions",
              "access": "read-write"
            },
            {
              "name": "MASK_UEP_R_TOG",
              "description": "endpoint 7 synchronous trigger bit for the accept to prepare",
              "access": "read-write"
            },
            {
              "name": "bUEP_R_TOG_AUTO",
              "description": "endpoint 7 synchronous trigger bit automatic filp enables the control bit",
              "access": "read-only"
            }
          ]
        },
        {
          "name": "UEP8_T_LEN",
          "description": "endpoint 8 send the length",
          "addressOffset": "0x00F8",
          "absoluteAddress": "0x400234F8",
          "size": 16,
          "access": "read-write",
          "fields": [
            {
              "name": "UEP8_T_LEN",
              "description": "endpoint 8 send the length",
              "access": "read-write"
            }
          ]
        },
        {
          "name": "UEP8_T_CTRL",
          "description": "endpoint 8 send control",
          "addressOffset": "0x00FA",
          "absoluteAddress": "0x400234FA",
          "size": 8,
          "access": "read-write",
          "fields": [
            {
              "name": "MASK_UEP_T_RES",
              "description": "endpoint 8 control of the send response to IN transactions",
              "access": "read-write"
            },
            {
              "name": "MASK_UEP_T_TOG",
              "description": "endpoint 8 synchronous trigger bit for the sender to prepare",
              "access": "read-write"
            },
            {
              "name": "bUEP_T_TOG_AUTO",
              "description": "endpoint 8 synchronous trigger bit automatic filp enables the control bit",
              "access": "read-write"
            }
          ]
        },
        {
          "name": "UEP8_R_CTRL",
          "description": "endpoint 8 send control",
          "addressOffset": "0x00FB",
          "absoluteAddress": "0x400234FB",
          "size": 8,
          "access": "read-write",
          "fields": [
            {
              "name": "MASK_UEP_R_RES",
              "description": "endpoint 8 control of the accept response to OUT transactions",
              "access": "read-write"
            },
            {
              "name": "MASK_UEP_R_TOG",
              "description": "endpoint 8 synchronous trigger bit for the accept to prepare",
              "access": "read-write"
            },
            {
              "name": "bUEP_R_TOG_AUTO",
              "description": "endpoint 8 synchronous trigger bit automatic filp enables the control bit",
              "access": "read-only"
            }
          ]
        },
        {
          "name": "UEP9_T_LEN",
          "description": "endpoint9 send the length",
          "addressOffset": "0x00FC",
          "absoluteAddress": "0x400234FC",
          "size": 16,
          "access": "read-write",
          "fields": [
            {
              "name": "UEP9_T_LEN",
              "description": "endpoint 9 send the length",
              "access": "read-write"
            }
          ]
        },
        {
          "name": "UEP9_T_CTRL",
          "description": "endpoint 9 send control",
          "addressOffset": "0x00FE",
          "absoluteAddress": "0x400234FE",
          "size": 8,
          "access": "read-write",
          "fields": [
            {
              "name": "MASK_UEP_T_RES",
              "description": "endpoint 9 control of the send response to IN transactions",
              "access": "read-write"
            },
            {
              "name": "MASK_UEP_T_TOG",
              "description": "endpoint 9 synchronous trigger bit for the sender to prepare",
              "access": "read-write"
            },
            {
              "name": "bUEP_T_TOG_AUTO",
              "description": "endpoint 9 synchronous trigger bit automatic filp enables the control bit",
              "access": "read-write"
            }
          ]
        },
        {
          "name": "UEP9_R_CTRL",
          "description": "endpoint 9 send control",
          "addressOffset": "0x00FF",
          "absoluteAddress": "0x400234FF",
          "size": 8,
          "access": "read-write",
          "fields": [
            {
              "name": "MASK_UEP_R_RES",
              "description": "endpoint 9 control of the accept response to OUT transactions",
              "access": "read-write"
            },
            {
              "name": "MASK_UEP_R_TOG",
              "description": "endpoint 9 synchronous trigger bit for the accept to prepare",
              "access": "read-write"
            },
            {
              "name": "bUEP_R_TOG_AUTO",
              "description": "endpoint 9 synchronous trigger bit automatic filp enables the control bit",
              "access": "read-only"
            }
          ]
        },
        {
          "name": "UEP10_T_LEN",
          "description": "endpoint 10 send the length",
          "addressOffset": "0x0100",
          "absoluteAddress": "0x40023500",
          "size": 16,
          "access": "read-write",
          "fields": [
            {
              "name": "UEP10_T_LEN",
              "description": "endpoint 10 send the length",
              "access": "read-write"
            }
          ]
        },
        {
          "name": "UEP10_T_CTRL",
          "description": "endpoint 10 send control",
          "addressOffset": "0x0102",
          "absoluteAddress": "0x40023502",
          "size": 8,
          "access": "read-write",
          "fields": [
            {
              "name": "MASK_UEP_T_RES",
              "description": "endpoint 10 control of the send response to IN transactions",
              "access": "read-write"
            },
            {
              "name": "MASK_UEP_T_TOG",
              "description": "endpoint 10 synchronous trigger bit for the sender to prepare",
              "access": "read-write"
            },
            {
              "name": "bUEP_T_TOG_AUTO",
              "description": "endpoint 10 synchronous trigger bit automatic filp enables the control bit",
              "access": "read-write"
            }
          ]
        },
        {
          "name": "UEP10_R_CTRL",
          "description": "endpoint 10 send control",
          "addressOffset": "0x0103",
          "absoluteAddress": "0x40023503",
          "size": 8,
          "access": "read-write",
          "fields": [
            {
              "name": "MASK_UEP_R_RES",
              "description": "endpoint 10 control of the accept response to OUT transactions",
              "access": "read-write"
            },
            {
              "name": "MASK_UEP_R_TOG",
              "description": "endpoint 10 synchronous trigger bit for the accept to prepare",
              "access": "read-write"
            },
            {
              "name": "bUEP_R_TOG_AUTO",
              "description": "endpoint 10 synchronous trigger bit automatic filp enables the control bit",
              "access": "read-only"
            }
          ]
        },
        {
          "name": "UEP11_T_LEN",
          "description": "endpoint 11 send the length",
          "addressOffset": "0x0104",
          "absoluteAddress": "0x40023504",
          "size": 16,
          "access": "read-write",
          "fields": [
            {
              "name": "UEP0_T_LEN",
              "description": "endpoint 11 send the length",
              "access": "read-write"
            }
          ]
        },
        {
          "name": "UEP11_T_CTRL",
          "description": "endpoint 11 send control",
          "addressOffset": "0x0106",
          "absoluteAddress": "0x40023506",
          "size": 8,
          "access": "read-write",
          "fields": [
            {
              "name": "MASK_UEP_T_RES",
              "description": "endpoint 11 control of the send response to IN transactions",
              "access": "read-write"
            },
            {
              "name": "MASK_UEP_T_TOG",
              "description": "endpoint 11 synchronous trigger bit for the sender to prepare",
              "access": "read-write"
            },
            {
              "name": "bUEP_T_TOG_AUTO",
              "description": "endpoint 11 synchronous trigger bit automatic filp enables the control bit",
              "access": "read-write"
            }
          ]
        },
        {
          "name": "UEP11_R_CTRL",
          "description": "endpoint 11 send control",
          "addressOffset": "0x0107",
          "absoluteAddress": "0x40023507",
          "size": 8,
          "access": "read-write",
          "fields": [
            {
              "name": "MASK_UEP_R_RES",
              "description": "endpoint 11 control of the accept response to OUT transactions",
              "access": "read-write"
            },
            {
              "name": "MASK_UEP_R_TOG",
              "description": "endpoint 11 synchronous trigger bit for the accept to prepare",
              "access": "read-write"
            },
            {
              "name": "bUEP_R_TOG_AUTO",
              "description": "endpoint 11 synchronous trigger bit automatic filp enables the control bit",
              "access": "read-only"
            }
          ]
        },
        {
          "name": "UEP12_T_LEN",
          "description": "endpoint 12 send the length",
          "addressOffset": "0x0108",
          "absoluteAddress": "0x40023508",
          "size": 16,
          "access": "read-write",
          "fields": [
            {
              "name": "UEP0_T_LEN",
              "description": "endpoint 12 send the length",
              "access": "read-write"
            }
          ]
        },
        {
          "name": "UEP12_T_CTRL",
          "description": "endpoint 12 send control",
          "addressOffset": "0x010A",
          "absoluteAddress": "0x4002350A",
          "size": 8,
          "access": "read-write",
          "fields": [
            {
              "name": "MASK_UEP_T_RES",
              "description": "endpoint 12 control of the send response to IN transactions",
              "access": "read-write"
            },
            {
              "name": "MASK_UEP_T_TOG",
              "description": "endpoint 12 synchronous trigger bit for the sender to prepare",
              "access": "read-write"
            },
            {
              "name": "bUEP_T_TOG_AUTO",
              "description": "endpoint 12 synchronous trigger bit automatic filp enables the control bit",
              "access": "read-write"
            }
          ]
        },
        {
          "name": "UEP12_R_CTRL",
          "description": "endpoint 12 send control",
          "addressOffset": "0x010B",
          "absoluteAddress": "0x4002350B",
          "size": 8,
          "access": "read-write",
          "fields": [
            {
              "name": "MASK_UEP_R_RES",
              "description": "endpoint 12 control of the accept response to OUT transactions",
              "access": "read-write"
            },
            {
              "name": "MASK_UEP_R_TOG",
              "description": "endpoint 12 synchronous trigger bit for the accept to prepare",
              "access": "read-write"
            },
            {
              "name": "bUEP_R_TOG_AUTO",
              "description": "endpoint 12 synchronous trigger bit automatic filp enables the control bit",
              "access": "read-only"
            }
          ]
        },
        {
          "name": "UEP13_T_LEN",
          "description": "endpoint 13 send the length",
          "addressOffset": "0x010C",
          "absoluteAddress": "0x4002350C",
          "size": 16,
          "access": "read-write",
          "fields": [
            {
              "name": "UEP13_T_LEN",
              "description": "endpoint 13 send the length",
              "access": "read-write"
            }
          ]
        },
        {
          "name": "UEP13_T_CTRL",
          "description": "endpoint 13 send control",
          "addressOffset": "0x010E",
          "absoluteAddress": "0x4002350E",
          "size": 8,
          "access": "read-write",
          "fields": [
            {
              "name": "MASK_UEP_T_RES",
              "description": "endpoint 13 control of the send response to IN transactions",
              "access": "read-write"
            },
            {
              "name": "MASK_UEP_T_TOG",
              "description": "endpoint 13 synchronous trigger bit for the sender to prepare",
              "access": "read-write"
            },
            {
              "name": "bUEP_T_TOG_AUTO",
              "description": "endpoint 13 synchronous trigger bit automatic filp enables the control bit",
              "access": "read-write"
            }
          ]
        },
        {
          "name": "UEP13_R_CTRL",
          "description": "endpoint 13 send control",
          "addressOffset": "0x010F",
          "absoluteAddress": "0x4002350F",
          "size": 8,
          "access": "read-write",
          "fields": [
            {
              "name": "MASK_UEP_R_RES",
              "description": "endpoint 13 control of the accept response to OUT transactions",
              "access": "read-write"
            },
            {
              "name": "MASK_UEP_R_TOG",
              "description": "endpoint 13 synchronous trigger bit for the accept to prepare",
              "access": "read-write"
            },
            {
              "name": "bUEP_R_TOG_AUTO",
              "description": "endpoint 13 synchronous trigger bit automatic filp enables the control bit",
              "access": "read-only"
            }
          ]
        },
        {
          "name": "UEP14_T_LEN",
          "description": "endpoint 14 send the length",
          "addressOffset": "0x0110",
          "absoluteAddress": "0x40023510",
          "size": 16,
          "access": "read-write",
          "fields": [
            {
              "name": "UEP14_T_LEN",
              "description": "endpoint 14 send the length",
              "access": "read-write"
            }
          ]
        },
        {
          "name": "UEP14_T_CTRL",
          "description": "endpoint 14 send control",
          "addressOffset": "0x0112",
          "absoluteAddress": "0x40023512",
          "size": 8,
          "access": "read-write",
          "fields": [
            {
              "name": "MASK_UEP_T_RES",
              "description": "endpoint 14 control of the send response to IN transactions",
              "access": "read-write"
            },
            {
              "name": "MASK_UEP_T_TOG",
              "description": "endpoint 14 synchronous trigger bit for the sender to prepare",
              "access": "read-write"
            },
            {
              "name": "bUEP_T_TOG_AUTO",
              "description": "endpoint 14 synchronous trigger bit automatic filp enables the control bit",
              "access": "read-write"
            }
          ]
        },
        {
          "name": "UEP14_R_CTRL",
          "description": "endpoint 14 send control",
          "addressOffset": "0x0113",
          "absoluteAddress": "0x40023513",
          "size": 8,
          "access": "read-write",
          "fields": [
            {
              "name": "MASK_UEP_R_RES",
              "description": "endpoint 14 control of the accept response to OUT transactions",
              "access": "read-write"
            },
            {
              "name": "MASK_UEP_R_TOG",
              "description": "endpoint 14 synchronous trigger bit for the accept to prepare",
              "access": "read-write"
            },
            {
              "name": "bUEP_R_TOG_AUTO",
              "description": "endpoint 14 synchronous trigger bit automatic filp enables the control bit",
              "access": "read-only"
            }
          ]
        },
        {
          "name": "UEP15_T_LEN",
          "description": "endpoint 15 send the length",
          "addressOffset": "0x0114",
          "absoluteAddress": "0x40023514",
          "size": 16,
          "access": "read-write",
          "fields": [
            {
              "name": "UEP0_T_LEN",
              "description": "endpoint 15 send the length",
              "access": "read-write"
            }
          ]
        },
        {
          "name": "UEP15_T_CTRL",
          "description": "endpoint 15 send control",
          "addressOffset": "0x0116",
          "absoluteAddress": "0x40023516",
          "size": 8,
          "access": "read-write",
          "fields": [
            {
              "name": "MASK_UEP_T_RES",
              "description": "endpoint 15 control of the send response to IN transactions",
              "access": "read-write"
            },
            {
              "name": "MASK_UEP_T_TOG",
              "description": "endpoint 15 synchronous trigger bit for the sender to prepare",
              "access": "read-write"
            },
            {
              "name": "bUEP_T_TOG_AUTO",
              "description": "endpoint 15 synchronous trigger bit automatic filp enables the control bit",
              "access": "read-write"
            }
          ]
        },
        {
          "name": "UEP15_R_CTRL",
          "description": "endpoint 15 send control",
          "addressOffset": "0x0117",
          "absoluteAddress": "0x40023517",
          "size": 8,
          "access": "read-write",
          "fields": [
            {
              "name": "MASK_UEP_R_RES",
              "description": "endpoint 15 control of the accept response to OUT transactions",
              "access": "read-write"
            },
            {
              "name": "MASK_UEP_R_TOG",
              "description": "endpoint 15 synchronous trigger bit for the accept to prepare",
              "access": "read-write"
            },
            {
              "name": "bUEP_R_TOG_AUTO",
              "description": "endpoint 15 synchronous trigger bit automatic filp enables the control bit",
              "access": "read-only"
            }
          ]
        }
      ]
    }
  ]
}
